<?xml version="1.0"?>
<!DOCTYPE PubmedArticleSet PUBLIC "-//NLM//DTD PubMedArticle, 1st January 2014//EN" "http://www.ncbi.nlm.nih.gov/corehtml/query/DTD/pubmed_140101.dtd">
<PubmedArticle>
    <MedlineCitation Owner="NLM" Status="MEDLINE">
        <PMID Version="1">18815</PMID>
        <DateCreated>
            <Year>1977</Year>
            <Month>09</Month>
            <Day>17</Day>
        </DateCreated>
        <DateCompleted>
            <Year>1977</Year>
            <Month>09</Month>
            <Day>17</Day>
        </DateCompleted>
        <DateRevised>
            <Year>2013</Year>
            <Month>11</Month>
            <Day>21</Day>
        </DateRevised>
        <Article PubModel="Print">
            <Journal>
                <ISSN IssnType="Print">0041-008X</ISSN>
                <JournalIssue CitedMedium="Print">
                    <Volume>40</Volume>
                    <Issue>3</Issue>
                    <PubDate>
                        <Year>1977</Year>
                        <Month>Jun</Month>
                    </PubDate>
                </JournalIssue>
                <Title>Toxicology and applied pharmacology</Title>
                <ISOAbbreviation>Toxicol. Appl. Pharmacol.</ISOAbbreviation>
            </Journal>
            <ArticleTitle>Dopamine and interscapular fat hemorrhage in the rat pup.</ArticleTitle>
            <Pagination>
                <MedlinePgn>427-35</MedlinePgn>
            </Pagination>
            <AuthorList CompleteYN="Y">
                <Author ValidYN="Y">
                    <LastName>Kitchin</LastName>
                    <ForeName>K T</ForeName>
                    <Initials>KT</Initials>
                </Author>
                <Author ValidYN="Y">
                    <LastName>DiStefano</LastName>
                    <ForeName>V</ForeName>
                    <Initials>V</Initials>
                </Author>
            </AuthorList>
            <Language>eng</Language>
            <PublicationTypeList>
                <PublicationType UI="D016428">Journal Article</PublicationType>
                <PublicationType UI="D013487">Research Support, U.S. Gov't, P.H.S.</PublicationType>
            </PublicationTypeList>
        </Article>
        <MedlineJournalInfo>
            <Country>UNITED STATES</Country>
            <MedlineTA>Toxicol Appl Pharmacol</MedlineTA>
            <NlmUniqueID>0416575</NlmUniqueID>
            <ISSNLinking>0041-008X</ISSNLinking>
        </MedlineJournalInfo>
        <ChemicalList>
            <Chemical>
                <RegistryNumber>0</RegistryNumber>
                <NameOfSubstance UI="D002250">Carbon Radioisotopes</NameOfSubstance>
            </Chemical>
            <Chemical>
                <RegistryNumber>EC 1.14.16.2</RegistryNumber>
                <NameOfSubstance UI="D014446">Tyrosine 3-Monooxygenase</NameOfSubstance>
            </Chemical>
            <Chemical>
                <RegistryNumber>VTD58H1Z2X</RegistryNumber>
                <NameOfSubstance UI="D004298">Dopamine</NameOfSubstance>
            </Chemical>
            <Chemical>
                <RegistryNumber>X4W3ENH1CV</RegistryNumber>
                <NameOfSubstance UI="D009638">Norepinephrine</NameOfSubstance>
            </Chemical>
        </ChemicalList>
        <CitationSubset>IM</CitationSubset>
        <MeshHeadingList>
            <MeshHeading>
                <DescriptorName MajorTopicYN="N" UI="D000273">Adipose Tissue</DescriptorName>
                <QualifierName MajorTopicYN="Y" UI="Q000187">drug effects</QualifierName>
            </MeshHeading>
            <MeshHeading>
                <DescriptorName MajorTopicYN="N" UI="D000818">Animals</DescriptorName>
            </MeshHeading>
            <MeshHeading>
                <DescriptorName MajorTopicYN="N" UI="D000831">Animals, Newborn</DescriptorName>
                <QualifierName MajorTopicYN="Y" UI="Q000502">physiology</QualifierName>
            </MeshHeading>
            <MeshHeading>
                <DescriptorName MajorTopicYN="N" UI="D002250">Carbon Radioisotopes</DescriptorName>
                <QualifierName MajorTopicYN="N" UI="Q000176">diagnostic use</QualifierName>
            </MeshHeading>
            <MeshHeading>
                <DescriptorName MajorTopicYN="N" UI="D004298">Dopamine</DescriptorName>
                <QualifierName MajorTopicYN="Y" UI="Q000009">adverse effects</QualifierName>
                <QualifierName MajorTopicYN="N" UI="Q000378">metabolism</QualifierName>
            </MeshHeading>
            <MeshHeading>
                <DescriptorName MajorTopicYN="N" UI="D005260">Female</DescriptorName>
            </MeshHeading>
            <MeshHeading>
                <DescriptorName MajorTopicYN="N" UI="D005865">Gestational Age</DescriptorName>
            </MeshHeading>
            <MeshHeading>
                <DescriptorName MajorTopicYN="N" UI="D006470">Hemorrhage</DescriptorName>
                <QualifierName MajorTopicYN="Y" UI="Q000139">chemically induced</QualifierName>
            </MeshHeading>
            <MeshHeading>
                <DescriptorName MajorTopicYN="N" UI="D008431">Maternal-Fetal Exchange</DescriptorName>
            </MeshHeading>
            <MeshHeading>
                <DescriptorName MajorTopicYN="N" UI="D009638">Norepinephrine</DescriptorName>
                <QualifierName MajorTopicYN="N" UI="Q000378">metabolism</QualifierName>
            </MeshHeading>
            <MeshHeading>
                <DescriptorName MajorTopicYN="N" UI="D011247">Pregnancy</DescriptorName>
            </MeshHeading>
            <MeshHeading>
                <DescriptorName MajorTopicYN="N" UI="D051381">Rats</DescriptorName>
            </MeshHeading>
            <MeshHeading>
                <DescriptorName MajorTopicYN="N" UI="D013997">Time Factors</DescriptorName>
            </MeshHeading>
            <MeshHeading>
                <DescriptorName MajorTopicYN="N" UI="D014446">Tyrosine 3-Monooxygenase</DescriptorName>
                <QualifierName MajorTopicYN="N" UI="Q000378">metabolism</QualifierName>
            </MeshHeading>
            <MeshHeading>
                <DescriptorName MajorTopicYN="N" UI="D014599">Uterus</DescriptorName>
                <QualifierName MajorTopicYN="N" UI="Q000201">enzymology</QualifierName>
                <QualifierName MajorTopicYN="N" UI="Q000378">metabolism</QualifierName>
            </MeshHeading>
            <MeshHeading>
                <DescriptorName MajorTopicYN="N" UI="D014621">Vagina</DescriptorName>
                <QualifierName MajorTopicYN="N" UI="Q000201">enzymology</QualifierName>
                <QualifierName MajorTopicYN="N" UI="Q000378">metabolism</QualifierName>
            </MeshHeading>
        </MeshHeadingList>
    </MedlineCitation>
    <PubmedData>
        <History>
            <PubMedPubDate PubStatus="pubmed">
                <Year>1977</Year>
                <Month>6</Month>
                <Day>1</Day>
            </PubMedPubDate>
            <PubMedPubDate PubStatus="medline">
                <Year>1977</Year>
                <Month>6</Month>
                <Day>1</Day>
                <Hour>0</Hour>
                <Minute>1</Minute>
            </PubMedPubDate>
            <PubMedPubDate PubStatus="entrez">
                <Year>1977</Year>
                <Month>6</Month>
                <Day>1</Day>
                <Hour>0</Hour>
                <Minute>0</Minute>
            </PubMedPubDate>
        </History>
        <PublicationStatus>ppublish</PublicationStatus>
        <ArticleIdList>
            <ArticleId IdType="pubmed">18815</ArticleId>
        </ArticleIdList>
    </PubmedData>
</PubmedArticle>
